socketio_emitter/__init__.py
socketio_emitter/consts.py
socketio_emitter/emitter.py
socketio_emitter/entities.py
socketio_emitter/py.typed
socket_io_redis_emitter-0.0.3.dist-info/METADATA
socket_io_redis_emitter-0.0.3.dist-info/WHEEL
socket_io_redis_emitter-0.0.3.dist-info/RECORD
