Metadata-Version: 2.1
Name: socket.io-redis-emitter
Version: 0.0.3
Summary: An asynchronous Redis-based Socket.IO emitter for Python
Home-page: https://github.com/roma-glushko/socket.io-redis-emitter
License: MIT
Keywords: socket.io,redis,websocket,emitter,library
Author: Roman Glushko
Author-email: roman.glushko.m@gmail.com
Requires-Python: >=3.8,<4.0
Classifier: License :: OSI Approved :: MIT License
Classifier: Programming Language :: Python :: 3
Classifier: Programming Language :: Python :: 3.8
Classifier: Programming Language :: Python :: 3.9
Classifier: Programming Language :: Python :: 3.10
Classifier: Programming Language :: Python :: 3.11
Classifier: Programming Language :: Python :: 3.12
Classifier: Topic :: Software Development :: Libraries :: Python Modules
Requires-Dist: msgpack (==1.0.8)
Requires-Dist: pydantic (==2.4.2)
Requires-Dist: redis[hiredis] (==5.0.2)
Project-URL: Repository, https://github.com/roma-glushko/socket.io-redis-emitter
